{
  "timestamp": "2026-07-13T20:52:36.977358-04:00",
  "time_display": "08:52 PM ET",
  "type": "closing",
  "games": {
    "American League @ National League": {
      "away": "American League",
      "home": "National League",
      "commence_time": "2026-07-15T00:01:00Z",
      "books": {
        "FanDuel": {
          "away_price": 120,
          "home_price": -142,
          "total_line": 7.5,
          "over_price": -122
        },
        "BetOnline.ag": {
          "away_price": 121,
          "home_price": -133,
          "total_line": 7.5,
          "over_price": -125
        },
        "BetUS": {
          "away_price": 121,
          "home_price": -133,
          "total_line": 8.0,
          "over_price": -120
        },
        "LowVig.ag": {
          "away_price": 121,
          "home_price": -133,
          "total_line": 7.5,
          "over_price": -123
        },
        "BetMGM": {
          "away_price": 115,
          "home_price": -140,
          "total_line": 8.0,
          "over_price": -110
        }
      }
    }
  }
}